invoke_databricks_wheel_tasks/__init__.py
invoke_databricks_wheel_tasks/tasks.py
invoke_databricks_wheel_tasks/utils/__init__.py
invoke_databricks_wheel_tasks/utils/databricks.py
invoke_databricks_wheel_tasks/utils/git.py
invoke_databricks_wheel_tasks/utils/misc.py
invoke_databricks_wheel_tasks/utils/poetry.py
invoke_databricks_wheel_tasks-0.8.0.dist-info/LICENSE
invoke_databricks_wheel_tasks-0.8.0.dist-info/WHEEL
invoke_databricks_wheel_tasks-0.8.0.dist-info/METADATA
invoke_databricks_wheel_tasks-0.8.0.dist-info/RECORD
