Metadata-Version: 2.1
Name: invoke-databricks-wheel-tasks
Version: 0.8.0
Summary: Databricks Python Wheel dev tasks in a namespaced collection of tasks to enrich the Invoke CLI task runner.
Home-page: https://github.com/neozenith/invoke-databricks-wheel-tasks
License: MIT
Author: Josh Peak
Author-email: neozenith.dev@gmail.com
Requires-Python: >=3.8,<4.0
Classifier: License :: OSI Approved :: MIT License
Classifier: Programming Language :: Python :: 3
Classifier: Programming Language :: Python :: 3.8
Classifier: Programming Language :: Python :: 3.9
Classifier: Programming Language :: Python :: 3.10
Classifier: Programming Language :: Python :: 3.11
Requires-Dist: Jinja2 (>=2.11.3)
Requires-Dist: databricks-cli (>=0.16.4,<0.17.0)
Requires-Dist: invoke (>=1.7.1,<2.0.0)
Requires-Dist: poetry-core (>=1.0.8,<2.0.0)
Project-URL: Repository, https://github.com/neozenith/invoke-databricks-wheel-tasks
